bitsy/__init__.py
bitsy/bitsy.py
bitsy-0.0.1.dist-info/LICENSE
bitsy-0.0.1.dist-info/METADATA
bitsy-0.0.1.dist-info/WHEEL
bitsy-0.0.1.dist-info/top_level.txt
bitsy-0.0.1.dist-info/RECORD
