Metadata-Version: 2.1
Name: bitsy
Version: 0.0.1
Summary: A Python tool to access 1D data bit wise.
Home-page: https://github.com/JaideepSagar1997/bitsy
Author: Jaideep Sagar
Author-email: jaideep.mcs17.du@gmail.com
License: UNKNOWN
Platform: UNKNOWN
Classifier: Programming Language :: Python :: 3
Classifier: Programming Language :: Python :: 3.4
Classifier: Programming Language :: Python :: 3.5
Classifier: Programming Language :: Python :: 3.6
Classifier: License :: OSI Approved :: MIT License
Classifier: Operating System :: OS Independent
Requires-Dist: numpy
